{"slug":"help","title":"help","description":"该命令是bash内建命令，用于显示bash内建命令的帮助信息。","sourcePath":"data/linux-command/command/help.md","markdown":"help\r\n===\r\n\r\n该命令是bash内建命令，用于显示bash内建命令的帮助信息。\r\n\r\n## 补充说明\r\n\r\n**help命令** help命令只能显示bash内建命令的帮助信息，而对于外部命令的帮助信息只能使用man或者info命令查看。\r\n\r\n###  语法\r\n\r\n```shell\r\nhelp(选项)(参数)\r\n```\r\n\r\n###  选项\r\n\r\n```shell\r\n-d：显示内建命令的简要描述。\r\n-m：按照man手册的格式输出内建命令的帮助信息。\r\n-s：仅输出内建命令的命令格式。\r\n不指定选项时：输出的帮助信息类似于-m选项，但是缺少段落名称和'SEE ALSO'，'IMPLEMENTATION'部分。\r\n```\r\n\r\n###  参数\r\n\r\nbash内建命令（可以为多个，请用空格分隔开）。\r\n\r\n### 常见问题\r\n\r\nQ：有哪些命令是bash内建命令？我如何判断一个命令是否为bash内建命令？\r\n\r\nA：您可以在终端使用 'man builtin' 或 'man builtins' 来获取；您可以查看bash内建命令 'type' 的帮助信息。\r\n\r\nQ：那么help命令本身的帮助信息如何获取？\r\n\r\nA：把help作为参数传给help命令；）\r\n\r\nQ：为什么echo也可以用 'man echo' 来查看帮助信息？\r\n\r\nA：因为除了bash内建的echo，GNU/linux的coreutils包里也有该命令；在echo的man手册中，DESCRIPTION段落的 'NOTE' 也提示了和同名内建的不同。\r\n\r\nPS：当你在shell脚本里定义了一个叫 'echo' 的函数，那么调用的时候优先级会如何呢？\r\n\r\n请参考 'builtin' 命令\r\n\r\nQ：我需要获得更多的bash的相关帮助信息\r\n\r\nA：限于篇幅和主题，您可以在终端执行 'man bash' ， 'info bash' ，[访问bash官方网站](http://www.gnu.org/software/bash/)，以及搜索引擎等。\r\n\r\n\r\n###  实例\r\n\r\n使用help命令显示shell内部shopt命令的帮助信息，输入如下命令：\r\n\r\n```shell\r\nhelp shopt                #获取shopt命令的帮助信息\r\nshopt: shopt [-pqsu] [-o long-option] optname [optname...]\r\n    Toggle the values of variables controlling optional behavior.\r\n    The -s flag means to enable (set) each OPTNAME; the -u flag\r\n    unsets each OPTNAME.  The -q flag suppresses output; the exit\r\n    status indicates whether each OPTNAME is set or unset.  The -o\r\n    option restricts the OPTNAMEs to those defined for use with\r\n    `set -o'.  With no options, or with the -p option, a list of all\r\n    settable options is displayed, with an indication of whether or\r\n    not each is set.\r\n```\r\n\r\n\r\n\r\n"}